[{"title":"Ode to Joy (Cover)","author":"muteKi"},{"title":"Last Christmas (Cover)","author":"Pieces Of Eight"},{"title":"Blessed Joy & Peace To The World (Covers)","author":"3ndymion"},{"title":"Dies ist der Tag den Gott gemacht (Cover)","author":"8tr"},{"title":"Santa's New Tech Beard","author":"Laffe the Fox"},{"title":"Peces en el rio (Cover)","author":"Calamarespaciales"},{"title":"Driedel (Cover)","author":".keanu."},{"title":"The Fantastic Mr Dog Pees on the Xmas Tree","author":"CLSource"},{"title":"Luciasång [Lucia Song] (Cover)","author":"Musho"}]